hydra_rhl/__init__.py
hydra_rhl/__main__.py
hydra_rhl/core/__init__.py
hydra_rhl/core/container.py
hydra_rhl/core/logger.py
hydra_rhl/examples/__init__.py
hydra_rhl/examples/eventConsumerExample.py
hydra_rhl/examples/event_producer_example.py
hydra_rhl/infra/__init__.py
hydra_rhl/infra/events/__init__.py
hydra_rhl/infra/events/consumer.py
hydra_rhl/infra/events/producer.py
hydra_rhl/infra/events/utils.py
hydra_rhl/infra/kafka/__init__.py
hydra_rhl/infra/kafka/kafka_hydra.py
hydra_rhl/settings/__init__.py
hydra_rhl/settings/config.py
hydra_rhl-0.2.dist-info/METADATA
hydra_rhl-0.2.dist-info/WHEEL
hydra_rhl-0.2.dist-info/top_level.txt
hydra_rhl-0.2.dist-info/RECORD
