Metadata-Version: 2.1
Name: hydra-rhl
Version: 0.2
Summary: RHL kafka management tool
Author-email: Redhuntlabs <rishabh.bhardwaj@redhuntlabs.com>
Classifier: Environment :: Web Environment
Classifier: Operating System :: OS Independent
Classifier: Programming Language :: Python
Classifier: Programming Language :: Python :: 3
Classifier: Programming Language :: Python :: 3 :: Only
Classifier: Programming Language :: Python :: 3.6
Classifier: Programming Language :: Python :: 3.7
Classifier: Programming Language :: Python :: 3.8
Requires-Python: >=3.6
Requires-Dist: dependency-injector (>=4.40.0)
Requires-Dist: kafka-python (>=2.0.2)
Requires-Dist: python-dotenv (>=0.21.0)
Provides-Extra: build
Requires-Dist: build ; extra == 'build'
Requires-Dist: twine ; extra == 'build'
